hass_smartthings_remove/__init__.py
hass_smartthings_remove/remove.py
hass_smartthings_remove-1.0.1.dist-info/LICENSE
hass_smartthings_remove-1.0.1.dist-info/METADATA
hass_smartthings_remove-1.0.1.dist-info/WHEEL
hass_smartthings_remove-1.0.1.dist-info/entry_points.txt
hass_smartthings_remove-1.0.1.dist-info/top_level.txt
hass_smartthings_remove-1.0.1.dist-info/RECORD
